.coveragerc
.gitattributes
AUTHORS.rst
CHANGES.rst
LICENSE.txt
MANIFEST.in
README.rst
notes
requirements.txt
setup.cfg
setup.py
versioneer.py
clusteror/__init__.py
clusteror/_version.py
clusteror/config.py
clusteror/core.py
clusteror/data_layer.py
clusteror/discovery_layer.py
clusteror/implementation_layer.py
clusteror/nn.py
clusteror/plot.py
clusteror/preprocessing_layer.py
clusteror/settings.py
clusteror/skeleton.py
clusteror/utils.py
clusteror/versioneer.py
clusteror.egg-info/PKG-INFO
clusteror.egg-info/SOURCES.txt
clusteror.egg-info/dependency_links.txt
clusteror.egg-info/not-zip-safe
clusteror.egg-info/requires.txt
clusteror.egg-info/top_level.txt
clusteror/api/clusteror.rst
clusteror/api/modules.rst
clusteror/api/tests.rst
clusteror/api/versioneer.rst
docs/authors.rst
docs/conf.py
docs/index.rst
docs/license.rst
docs/notes
docs/_build/doctrees/author.doctree
docs/_build/doctrees/authors.doctree
docs/_build/doctrees/environment.pickle
docs/_build/doctrees/index.doctree
docs/_build/doctrees/license.doctree
docs/_build/doctrees/api/autoindex.doctree
docs/_build/doctrees/api/clusteror._version.doctree
docs/_build/doctrees/api/clusteror.config.doctree
docs/_build/doctrees/api/clusteror.core.doctree
docs/_build/doctrees/api/clusteror.data_layer.doctree
docs/_build/doctrees/api/clusteror.discovery_layer.doctree
docs/_build/doctrees/api/clusteror.doctree
docs/_build/doctrees/api/clusteror.implementation_layer.doctree
docs/_build/doctrees/api/clusteror.nn.doctree
docs/_build/doctrees/api/clusteror.plot.doctree
docs/_build/doctrees/api/clusteror.preprocessing_layer.doctree
docs/_build/doctrees/api/clusteror.settings.doctree
docs/_build/doctrees/api/clusteror.skeleton.doctree
docs/_build/doctrees/api/clusteror.utils.doctree
docs/_build/doctrees/api/clusteror.versioneer.doctree
docs/_build/doctrees/api/modules.doctree
docs/_build/doctrees/api/tests.doctree
docs/_build/doctrees/api/versioneer.doctree
docs/_build/doctrees/bak_api/autoindex.doctree
docs/_build/doctrees/bak_api/clusteror._version.doctree
docs/_build/doctrees/bak_api/clusteror.config.doctree
docs/_build/doctrees/bak_api/clusteror.core.doctree
docs/_build/doctrees/bak_api/clusteror.data_layer.doctree
