Metadata-Version: 1.1
Name: clusteror
Version: 0.0.2
Summary: Dataset pattern discovery tool
Home-page: http://...
Author: Fei Zhan
Author-email: enfeizhan@gmail.com
License: none
Platform: any
Classifier: Development Status :: 4 - Beta
Classifier: Programming Language :: Python
